LICENSE
README.md
setup.py
nuvola/__init__.py
nuvola/nuvola.py
nuvola/version.py
nuvola.egg-info/PKG-INFO
nuvola.egg-info/SOURCES.txt
nuvola.egg-info/dependency_links.txt
nuvola.egg-info/requires.txt
nuvola.egg-info/top_level.txt