Metadata-Version: 2.1
Name: nuvola
Version: 1.4
Summary: Python API for the electronic register Nuvola from Madisoft
Home-page: https://github.com/topongo/nuvola
Author: Lorenzo Bodini
Author-email: lorenzo.bodini.private@gmail.com
License: GPL3
Platform: UNKNOWN
Requires-Python: >=3.7
License-File: LICENSE
